openpy_fx_tools_dss/__init__.py
openpy_fx_tools_dss/data_from_DSS/__init__.py
openpy_fx_tools_dss/data_from_DSS/help_DSS/ClassName.xlsx
openpy_fx_tools_dss/data_from_DSS/help_DSS/DSSHelp.csv
openpy_fx_tools_dss/data_from_DSS/help_DSS/DSSHelp.Txt
openpy_fx_tools_dss/data_from_DSS/help_DSS/DSSHelp_Default.xlsx
openpy_fx_tools_dss/data_from_DSS/parameters/__init__.py
openpy_fx_tools_dss/data_from_DSS/results/__init__.py
openpy_fx_tools_dss/Examples/123Bus/DSS_files/BusCoords.dat
openpy_fx_tools_dss/Examples/123Bus/DSS_files/CircuitPlottingScripts.dss
openpy_fx_tools_dss/Examples/123Bus/DSS_files/ieee123_Curr_Elem.Txt
openpy_fx_tools_dss/Examples/123Bus/DSS_files/ieee123_Daisy.dbl
openpy_fx_tools_dss/Examples/123Bus/DSS_files/ieee123_Daisy.DSV
openpy_fx_tools_dss/Examples/123Bus/DSS_files/ieee123_Loadshape_default.dbl
openpy_fx_tools_dss/Examples/123Bus/DSS_files/ieee123_Loadshape_default.DSV
openpy_fx_tools_dss/Examples/123Bus/DSS_files/ieee123_Losses.dbl
openpy_fx_tools_dss/Examples/123Bus/DSS_files/ieee123_Losses.DSV
openpy_fx_tools_dss/Examples/123Bus/DSS_files/ieee123_Mon_4a_1.csv
openpy_fx_tools_dss/Examples/123Bus/DSS_files/ieee123_Mon_mon1_1.csv
openpy_fx_tools_dss/Examples/123Bus/DSS_files/ieee123_Mon_p4a_1.csv
openpy_fx_tools_dss/Examples/123Bus/DSS_files/ieee123_MONITOR-4A-ch1.dbl
openpy_fx_tools_dss/Examples/123Bus/DSS_files/ieee123_MONITOR-4A-ch1.DSV
openpy_fx_tools_dss/Examples/123Bus/DSS_files/ieee123_MONITOR-P4A-ch1.dbl
openpy_fx_tools_dss/Examples/123Bus/DSS_files/ieee123_MONITOR-P4A-ch1.DSV
openpy_fx_tools_dss/Examples/123Bus/DSS_files/ieee123_Power.dbl
openpy_fx_tools_dss/Examples/123Bus/DSS_files/ieee123_Power.DSV
openpy_fx_tools_dss/Examples/123Bus/DSS_files/ieee123_Power_elem_kVA.txt
openpy_fx_tools_dss/Examples/123Bus/DSS_files/ieee123_Profile9998.dbl
openpy_fx_tools_dss/Examples/123Bus/DSS_files/ieee123_Profile9998.DSV
openpy_fx_tools_dss/Examples/123Bus/DSS_files/ieee123_Profile9999.dbl
openpy_fx_tools_dss-0.1.6.dist-info/LICENSE.md
openpy_fx_tools_dss-0.1.6.dist-info/METADATA
openpy_fx_tools_dss-0.1.6.dist-info/WHEEL
openpy_fx_tools_dss-0.1.6.dist-info/RECORD
