Metadata-Version: 2.1
Name: openpy-fx-tools-dss
Version: 0.1.6
Summary: Python functions for extracting, executing routines, etc. from projects modeled in OpenDSS
Home-page: https://github.com/jlara6/OpenPy-fx-tools-DSS
License: LICENSE
Keywords: OpenDSS,Distribution stystem,Python,smart grid,openpy-fx-tools-dss,openpy_fx_tools_dss
Author: Jorge A. Lara S.
Author-email: jlara@iee.unsj.edu.ar
Maintainer: Jorge A. Lara S.
Maintainer-email: jlara@iee.unsj.edu.ar
Requires-Python: >=3.8,<4.0
Classifier: License :: Other/Proprietary License
Classifier: Programming Language :: Python :: 3
Classifier: Programming Language :: Python :: 3.8
Classifier: Programming Language :: Python :: 3.9
Classifier: Programming Language :: Python :: 3.10
Classifier: Programming Language :: Python :: 3.11
Requires-Dist: colorama (==0.4.6)
Requires-Dist: numpy (==1.23.5)
Requires-Dist: opendssdirect-py (==0.7.0)
Requires-Dist: openpyxl (==3.0.10)
Requires-Dist: pandas (==1.5.2)
Requires-Dist: py-dss-interface (==1.0.2)
Project-URL: Repository, https://github.com/jlara6/OpenPy-fx-tools-DSS
